fetchmd/__init__.py
fetchmd/cli.py
fetchmd/core.py
fetchmd-0.1.0.dist-info/METADATA
fetchmd-0.1.0.dist-info/WHEEL
fetchmd-0.1.0.dist-info/entry_points.txt
fetchmd-0.1.0.dist-info/licenses/LICENSE
fetchmd-0.1.0.dist-info/RECORD
