Metadata-Version: 2.4
Name: fetchmd
Version: 0.1.0
Summary: Python library and CLI to fetch any web page as Markdown
Project-URL: Homepage, https://github.com/niksite/fetchmd
Project-URL: Repository, https://github.com/niksite/fetchmd
Project-URL: Issues, https://github.com/niksite/fetchmd/issues
Author-email: Nikolay Panov <github@npanov.com>
License: MIT License
License-File: LICENSE
Requires-Python: >=3.10
Requires-Dist: html2text
Requires-Dist: httpx
Requires-Dist: lxml
Requires-Dist: readability-lxml
